{"5":[{"warning":"5:lib\/less\/browser.js:W089:for(var func in less.functions) {","count":1,"result_id":11933},{"warning":"5:lib\/less\/functions.js:W089:for (f in mathFunctions) {","count":1,"result_id":11933},{"warning":"5:lib\/less\/functions.js:W089:for (f in colorBlendMode) {","count":1,"result_id":11933},{"warning":"5:lib\/less\/index.js:W089:for (var k in less) { exports[k] = less[k]; }","count":1,"result_id":11933},{"warning":"5:lib\/less\/lessc_helper.js:W089:for (var h in lessc_helper) { exports[h] = lessc_helper[h]; }","count":1,"result_id":11933},{"warning":"5:lib\/less\/source-map-output.js:W089:for(var filename in this._contentsMap) {","count":1,"result_id":11933},{"warning":"5:lib\/less\/tree\/javascript.js:W089:for (var k in env.frames[0].variables()) {","count":1,"result_id":11933},{"warning":"5:lib\/less\/tree\/mixin.js:W089:for (m in candidates) {","count":1,"result_id":11933},{"warning":"5:lib\/less\/visitor.js:W089:for (key in parent) {","count":1,"result_id":11933},{"warning":"5:bin\/lessc:W084:if (match = arg.match(\/^-I(.+)$\/)) {","count":173,"result_id":11796},{"warning":"5:bin\/lessc:W084:if (match = arg.match(\/^--?([a-z][0-9a-z-]*)(?:=(.*))?$\/i)) { arg = match[1] }","count":173,"result_id":11796},{"warning":"5:bin\/lessc:W089:for(var file in parser.imports.files) {","count":138,"result_id":11796}],"16":[{"warning":"16:bin\/lessc:W033:if (match = arg.match(\/^--?([a-z][0-9a-z-]*)(?:=(.*))?$\/i)) { arg = match[1] }","count":204,"result_id":11796},{"warning":"16:bin\/lessc:W033:if (options.lint) { writeSourceMap = function() {} }","count":81,"result_id":11796},{"warning":"16:bin\/lessc:W033:process.stdout.write(file + \" \")","count":20,"result_id":11796}],"7":[{"warning":"7:lib\/less\/functions.js:W003:function _math(fn, unit, n) {","count":148,"result_id":11796},{"warning":"7:lib\/less\/tree\/color.js:W003:function toHex(v) {","count":145,"result_id":11796},{"warning":"7:lib\/less\/tree\/color.js:W003:function clamp(v, max) {","count":145,"result_id":11796},{"warning":"7:lib\/less\/tree\/rule.js:W003:function evalName(env, name) {","count":112,"result_id":11796},{"warning":"7:lib\/less\/functions\/color.js:W003:var m2 = l <= 0.5 ? l * (s + 1) : l + s - l * s;","count":241,"result_id":11555},{"warning":"7:lib\/less\/functions\/color.js:W003:var m1 = l * 2 - m2;","count":241,"result_id":11555},{"warning":"7:lib\/less\/parser\/parser-input.js:W003:var CHARCODE_SPACE = 32,","count":241,"result_id":11555},{"warning":"7:lib\/less\/parser\/parser-input.js:W003:CHARCODE_TAB = 9,","count":241,"result_id":11555},{"warning":"7:lib\/less\/parser\/parser-input.js:W003:CHARCODE_LF = 10,","count":241,"result_id":11555},{"warning":"7:lib\/less\/parser\/parser-input.js:W003:CHARCODE_CR = 13,","count":241,"result_id":11555},{"warning":"7:lib\/less\/parser\/parser-input.js:W003:var skipWhitespace = function(length) {","count":241,"result_id":11555},{"warning":"7:lib\/less\/parser\/parser.js:W003:function error(msg, type) {","count":241,"result_id":11555},{"warning":"7:lib\/less\/tree\/unit.js:W003:for (var groupName in unitConversions) {","count":241,"result_id":11555},{"warning":"7:lib\/less-browser\/error-reporting.js:W003:function errorConsole(e, rootHref) {","count":241,"result_id":11555},{"warning":"7:lib\/less\/tree\/ruleset.js:W003:function addReplacementIntoPath(beginningPath, addPath, replacedElement, originalSelector) {","count":110,"result_id":11555},{"warning":"7:lib\/less\/tree\/ruleset.js:W003:function addAllReplacementsIntoPath( beginningPath, addPaths, replacedElement, originalSelector, result) {","count":110,"result_id":11555},{"warning":"7:lib\/less\/tree\/ruleset.js:W003:function mergeElementsOnToSelectors(elements, selectors) {","count":110,"result_id":11555}],"8":[{"warning":"8:lib\/less\/parser.js:W014:? value : new(tree.Anonymous)(value), env.currentFileInfo);","count":1,"result_id":11588},{"warning":"8:lib\/less\/parser.js:W014:? new(tree.Keyword)(s)","count":1,"result_id":11588},{"warning":"8:lib\/less\/tree\/mixin.js:W014:+ this.format(args) + '`',","count":1,"result_id":11588}],"14":[{"warning":"14:Gruntfile.js:W098:var fs = require('fs');","count":2,"result_id":11572}]}